{"records":[{"id":"rec8qz183nbeNENVY","createdTime":"2022-09-22T06:20:02.000Z","fields":{"Key":"intro.updated_at","Copy":"Intro updated on {updated_at, datetime}"}},{"id":"recP8WPBzyufHEGur","createdTime":"2022-09-22T06:16:39.000Z","fields":{"Key":"greetingVIP","Copy":"{greeting} You're on the VIP plan."}},{"id":"recY4PCdPgLrwyqyg","createdTime":"2022-09-22T06:16:39.000Z","fields":{"Key":"intro.created_at","Copy":"Intro created on {created_at, datetime}"}},{"id":"recv2s3VKrVK1zyaM","createdTime":"2022-09-22T06:16:39.000Z","fields":{"Key":"greeting","Copy":"Hi {name}, welcome to {app}!"}}]}